{
  "headers": {
    "x-amz-replication-status": "COMPLETED",
    "x-amz-cf-pop": "FRA56-P5",
    "content-type": "application/javascript",
    "access-control-allow-origin": "*",
    "via": "http/2 edgeproxy-h",
    "etag": "W/\"1f9af144e0ab9e36ab84af1fe67024a7\"",
    "server": "deno/gcp-europe-west3",
    "x-amz-version-id": "II3Il3TfeMxAje3.9jtQivT4.x0GBZDl",
    "x-cache": "Hit from cloudfront",
    "date": "Thu, 28 Dec 2023 01:09:07 GMT",
    "strict-transport-security": "max-age=63072000; includeSubDomains; preload",
    "x-content-type-options": "nosniff",
    "x-amz-cf-id": "Pd__61y8ewr6m0eKBbqKm-My5wa3GuCo8ZBcw6abdcU9-VYRLbTRcw==",
    "accept-ranges": "bytes",
    "age": "24142313",
    "last-modified": "Fri, 25 Mar 2022 13:32:50 GMT",
    "cross-origin-resource-policy": "same-origin",
    "vary": "Accept-Encoding, Origin",
    "x-frame-options": "DENY",
    "content-security-policy": "default-src 'none'; style-src 'unsafe-inline'; sandbox",
    "cross-origin-opener-policy": "same-origin",
    "server-timing": "fetchSource;dur=8",
    "referrer-policy": "strict-origin-when-cross-origin",
    "cross-origin-embedder-policy": "same-origin",
    "cache-control": "public, max-age=31536000, immutable"
  },
  "url": "https://deno.land/std@0.132.0/node/internal/crypto/util.mjs",
  "now": {
    "secs_since_epoch": 1727868059,
    "nanos_since_epoch": 298332526
  }
}